peerprint/__init__.py
peerprint/client.py
peerprint/comms.py
peerprint/comms_test.py
peerprint/filesharing.py
peerprint/filesharing_test.py
peerprint/ipfs.py
peerprint/ipfs_test.py
peerprint/proc.py
peerprint/proc_test.py
peerprint/server.py
peerprint/server_test.py
peerprint/version.py
peerprint/bin/__init__.py
peerprint/bin/server-linux-amd64
peerprint/bin/server-linux-arm64
peerprint/bin/server-windows-amd64.exe
peerprint/bin/server-windows-arm64.exe
peerprint/data/__init__.py
peerprint/data/psk_gen.py
peerprint/example/__init__.py
peerprint/example/main.py
peerprint/pkg/__init__.py
peerprint/pkg/proto/__init__.py
peerprint/pkg/proto/command_pb2.py
peerprint/pkg/proto/command_pb2_grpc.py
peerprint/pkg/proto/peers_pb2.py
peerprint/pkg/proto/state_pb2.py
peerprint/scripts/__init__.py
peerprint/scripts/cert_gen.py
peerprint/scripts/psk_gen.py
peerprint/scripts/trust_sim.py
peerprint-0.3.1.dist-info/LICENSE
peerprint-0.3.1.dist-info/METADATA
peerprint-0.3.1.dist-info/WHEEL
peerprint-0.3.1.dist-info/top_level.txt
peerprint-0.3.1.dist-info/RECORD
