Metadata-Version: 2.1
Name: peerprint
Version: 0.3.1
Summary: Peer-to-peer networked 3d printing
Home-page: https://github.com/smartin015/peerprint
Author: Scott Martin
Author-email: smartin015+peerprint@gmali.com
Project-URL: Bug Tracker, https://github.com/smartin015/peerprint
Classifier: Programming Language :: Python :: 3
Classifier: License :: OSI Approved :: Apache Software License
Classifier: Operating System :: OS Independent
Requires-Python: >=3.6
License-File: LICENSE
Requires-Dist: grpcio (==1.51.1)
Requires-Dist: protobuf (==4.21.8)
Requires-Dist: pyopenssl (>=23.0.0)
